ddd_objects/__init__.py
ddd_objects/lib.py
ddd_objects/application/__init__.py
ddd_objects/application/action.py
ddd_objects/application/assembler.py
ddd_objects/application/dto.py
ddd_objects/domain/__init__.py
ddd_objects/domain/entity.py
ddd_objects/domain/exception.py
ddd_objects/domain/operator.py
ddd_objects/domain/repository.py
ddd_objects/domain/value_obj.py
ddd_objects/infrastructure/__init__.py
ddd_objects/infrastructure/ao.py
ddd_objects/infrastructure/converter.py
ddd_objects/infrastructure/do.py
ddd_objects/infrastructure/repository_impl.py
ddd_objects/template/__init__.py
ddd_objects/template/base.py
ddd_objects/template/lib.py
ddd_objects/template/object_generator.py
ddd_objects-0.3.25.dist-info/LICENSE
ddd_objects-0.3.25.dist-info/METADATA
ddd_objects-0.3.25.dist-info/WHEEL
ddd_objects-0.3.25.dist-info/top_level.txt
ddd_objects-0.3.25.dist-info/RECORD
